arctans/__init__.py
arctans/arctans.py
arctans/core.py
arctans/generation.py
arctans/numbers.py
arctans/primes.py
arctans/py.typed
arctans/reduction.py
arctans-1.0.0.dist-info/licenses/LICENSE
arctans-1.0.0.dist-info/METADATA
arctans-1.0.0.dist-info/WHEEL
arctans-1.0.0.dist-info/top_level.txt
arctans-1.0.0.dist-info/RECORD
