Metadata-Version: 2.4
Name: arctans
Version: 1.0.0
Summary: a library for reducing arctans
Author-email: Matthew Scroggs <arctans@mscroggs.co.uk>
License-Expression: MIT
Project-URL: homepage, https://github.com/mscroggs/arctans
Project-URL: repository, https://github.com/mscroggs/arctans
Requires-Python: >=3.10.0
License-File: LICENSE
Requires-Dist: typing_extensions; python_version < "3.11"
Provides-Extra: style
Requires-Dist: ruff; extra == "style"
Requires-Dist: mypy; extra == "style"
Provides-Extra: docs
Requires-Dist: sphinx; extra == "docs"
Requires-Dist: sphinx-autoapi; extra == "docs"
Provides-Extra: test
Requires-Dist: pytest; extra == "test"
Dynamic: license-file
